learning_credentials/__init__.py
learning_credentials/admin.py
learning_credentials/apps.py
learning_credentials/compat.py
learning_credentials/exceptions.py
learning_credentials/generators.py
learning_credentials/models.py
learning_credentials/processors.py
learning_credentials/tasks.py
learning_credentials/urls.py
learning_credentials/api/__init__.py
learning_credentials/api/urls.py
learning_credentials/api/v1/__init__.py
learning_credentials/api/v1/permissions.py
learning_credentials/api/v1/urls.py
learning_credentials/api/v1/views.py
learning_credentials/conf/locale/config.yaml
learning_credentials/migrations/0001_initial.py
learning_credentials/migrations/0002_migrate_to_learning_credentials.py
learning_credentials/migrations/0003_rename_certificates_to_credentials.py
learning_credentials/migrations/0004_replace_course_keys_with_learning_context_keys.py
learning_credentials/migrations/0005_rename_processors_and_generators.py
learning_credentials/migrations/0006_cleanup_openedx_certificates_tables.py
learning_credentials/migrations/__init__.py
learning_credentials/settings/__init__.py
learning_credentials/settings/common.py
learning_credentials/settings/production.py
learning_credentials/templates/learning_credentials/base.html
learning_credentials/templates/learning_credentials/edx_ace/certificate_generated/email/body.html
learning_credentials/templates/learning_credentials/edx_ace/certificate_generated/email/body.txt
learning_credentials/templates/learning_credentials/edx_ace/certificate_generated/email/from_name.txt
learning_credentials/templates/learning_credentials/edx_ace/certificate_generated/email/head.html
learning_credentials/templates/learning_credentials/edx_ace/certificate_generated/email/subject.txt
learning_credentials-0.3.0.dist-info/licenses/LICENSE.txt
learning_credentials-0.3.0.dist-info/METADATA
learning_credentials-0.3.0.dist-info/WHEEL
learning_credentials-0.3.0.dist-info/entry_points.txt
learning_credentials-0.3.0.dist-info/top_level.txt
learning_credentials-0.3.0.dist-info/RECORD
