Metadata-Version: 2.4
Name: learning-credentials
Version: 0.3.0
Summary: A pluggable service for preparing Open edX credentials.
Author-email: OpenCraft <help@opencraft.com>
License-Expression: AGPL-3.0-or-later
Project-URL: Homepage, https://github.com/open-craft/learning-credentials
Project-URL: Repository, https://github.com/open-craft/learning-credentials
Project-URL: Documentation, https://learning-credentials.readthedocs.io/
Keywords: Python,edx,credentials,django
Classifier: Development Status :: 5 - Production/Stable
Classifier: Framework :: Django
Classifier: Framework :: Django :: 4.2
Classifier: Intended Audience :: Developers
Classifier: Natural Language :: English
Classifier: Programming Language :: Python :: 3
Classifier: Programming Language :: Python :: 3.11
Classifier: Programming Language :: Python :: 3.12
Requires-Python: >=3.11
License-File: LICENSE.txt
Requires-Dist: django
Requires-Dist: django-model-utils
Requires-Dist: edx-api-doc-tools
Requires-Dist: edx-django-utils
Requires-Dist: edx-opaque-keys
Requires-Dist: celery
Requires-Dist: django-celery-beat
Requires-Dist: django_reverse_admin
Requires-Dist: djangorestframework
Requires-Dist: django-object-actions
Requires-Dist: pypdf
Requires-Dist: reportlab
Requires-Dist: openedx-completion-aggregator
Requires-Dist: edx_ace
Requires-Dist: learning-paths-plugin>=0.3.4
Dynamic: license-file
